aug/Augmentation.py
aug/__init__.py
SpaceAugmentation-0.0.2.dist-info/LICENCE.txt
SpaceAugmentation-0.0.2.dist-info/METADATA
SpaceAugmentation-0.0.2.dist-info/WHEEL
SpaceAugmentation-0.0.2.dist-info/top_level.txt
SpaceAugmentation-0.0.2.dist-info/RECORD
